odoo/addons/invader_payment_stripe/README.rst
odoo/addons/invader_payment_stripe/__init__.py
odoo/addons/invader_payment_stripe/__manifest__.py
odoo/addons/invader_payment_stripe/data/decimal_precision.xml
odoo/addons/invader_payment_stripe/i18n/invader_payment_stripe.pot
odoo/addons/invader_payment_stripe/models/__init__.py
odoo/addons/invader_payment_stripe/models/invader_payable.py
odoo/addons/invader_payment_stripe/readme/CONTRIBUTORS.rst
odoo/addons/invader_payment_stripe/readme/DESCRIPTION.rst
odoo/addons/invader_payment_stripe/services/__init__.py
odoo/addons/invader_payment_stripe/services/payment_stripe.py
odoo/addons/invader_payment_stripe/static/description/icon.png
odoo/addons/invader_payment_stripe/static/description/index.html
odoo14_addon_invader_payment_stripe-14.0.1.0.2.dist-info/METADATA
odoo14_addon_invader_payment_stripe-14.0.1.0.2.dist-info/WHEEL
odoo14_addon_invader_payment_stripe-14.0.1.0.2.dist-info/top_level.txt
odoo14_addon_invader_payment_stripe-14.0.1.0.2.dist-info/RECORD
