Metadata-Version: 2.1
Name: odoo14-addon-invader-payment-stripe
Version: 14.0.1.0.2
Summary: REST Services for Stripe Payments (base module)
Home-page: https://github.com/shopinvader/odoo-shopinvader-payment
Author: ACSONE SA/NV
License: AGPL-3
Platform: UNKNOWN
Classifier: Programming Language :: Python
Classifier: Framework :: Odoo
Classifier: Framework :: Odoo :: 14.0
Classifier: License :: OSI Approved :: GNU Affero General Public License v3
Requires-Python: >=3.6
Requires-Dist: cerberus
Requires-Dist: odoo14-addon-base-rest
Requires-Dist: odoo14-addon-invader-payment
Requires-Dist: odoo (<14.1dev,>=14.0a)
Requires-Dist: stripe
